.gitignore
LICENSE
MANIFEST.in
README.md
pyproject.toml
setup.py
loco_mujoco/__init__.py
loco_mujoco.egg-info/PKG-INFO
loco_mujoco.egg-info/SOURCES.txt
loco_mujoco.egg-info/dependency_links.txt
loco_mujoco.egg-info/entry_points.txt
loco_mujoco.egg-info/requires.txt
loco_mujoco.egg-info/top_level.txt
loco_mujoco/algorithms/__init__.py
loco_mujoco/algorithms/amp_jax.py
loco_mujoco/algorithms/gail_jax.py
loco_mujoco/algorithms/ppo_jax.py
loco_mujoco/algorithms/common/__init__.py
loco_mujoco/algorithms/common/base_algorithm.py
loco_mujoco/algorithms/common/dataclasses.py
loco_mujoco/algorithms/common/networks.py
loco_mujoco/core/__init__.py
loco_mujoco/core/mujoco_base.py
loco_mujoco/core/mujoco_mjx.py
loco_mujoco/core/stateful_object.py
loco_mujoco/core/control_functions/__init__.py
loco_mujoco/core/control_functions/base.py
loco_mujoco/core/control_functions/default.py
loco_mujoco/core/control_functions/pd.py
loco_mujoco/core/domain_randomizer/__init__.py
loco_mujoco/core/domain_randomizer/base.py
loco_mujoco/core/domain_randomizer/default.py
loco_mujoco/core/domain_randomizer/no_randomization.py
loco_mujoco/core/initial_state_handler/__init__.py
loco_mujoco/core/initial_state_handler/base.py
loco_mujoco/core/initial_state_handler/default.py
loco_mujoco/core/initial_state_handler/traj_init_state.py
loco_mujoco/core/observations/__init__.py
loco_mujoco/core/observations/base.py
loco_mujoco/core/observations/goals.py
loco_mujoco/core/observations/visualizer.py
loco_mujoco/core/reward/__init__.py
loco_mujoco/core/reward/base.py
loco_mujoco/core/reward/default.py
loco_mujoco/core/reward/trajectory_based.py
loco_mujoco/core/reward/utils.py
loco_mujoco/core/terminal_state_handler/__init__.py
loco_mujoco/core/terminal_state_handler/base.py
loco_mujoco/core/terminal_state_handler/height.py
loco_mujoco/core/terminal_state_handler/no_terminal.py
loco_mujoco/core/terminal_state_handler/traj.py
loco_mujoco/core/terrain/__init__.py
loco_mujoco/core/terrain/base.py
loco_mujoco/core/terrain/dynamic.py
loco_mujoco/core/terrain/rough.py
loco_mujoco/core/terrain/static.py
loco_mujoco/core/utils/__init__.py
loco_mujoco/core/utils/backend.py
loco_mujoco/core/utils/decorators.py
