Metadata-Version: 2.1
Name: loco-mujoco
Version: 1.0.0
Summary: Imitation learning benchmark focusing on complex locomotion tasks using MuJoCo.
Home-page: https://github.com/robfiras/loco-mujoco
Author: Firas Al-Hafez
Author-email: Firas Al-Hafez <fi.alhafez@gmail.com>
Maintainer-email: Firas Al-Hafez <fi.alhafez@gmail.com>
License: MIT License
Project-URL: Homepage, https://github.com/robfiras/loco-mujoco
Project-URL: Repository, https://github.com/robfiras/loco-mujoco
Project-URL: Issues, https://github.com/robfiras/loco-mujoco/issues
Keywords: Imitation Learning,Reinforcement Learning,Locomotion
Classifier: Programming Language :: Python :: 3
Classifier: License :: OSI Approved :: MIT License
Classifier: Operating System :: OS Independent
Requires-Python: >=3.10
License-File: LICENSE
Requires-Dist: numpy<2.0
Requires-Dist: scipy>=1.14.0
Requires-Dist: mujoco==3.2.7
Requires-Dist: mujoco-mjx==3.2.7
Requires-Dist: hydra-core
Requires-Dist: jax
Requires-Dist: flax
Requires-Dist: orbax
Requires-Dist: distrax
Requires-Dist: metrx
Requires-Dist: gymnasium
Requires-Dist: pyyaml
Requires-Dist: opencv-python
Requires-Dist: wget
Requires-Dist: gitpython
Requires-Dist: datasets
Requires-Dist: huggingface_hub
